aidol/__init__.py
aidol/api/__init__.py
aidol/api/aidol.py
aidol/api/common.py
aidol/api/companion.py
aidol/api/lead.py
aidol/factories.py
aidol/models/__init__.py
aidol/models/aidol.py
aidol/models/aidol_lead.py
aidol/models/companion.py
aidol/protocols.py
aidol/py.typed
aidol/repositories/__init__.py
aidol/repositories/aidol.py
aidol/repositories/aidol_lead.py
aidol/repositories/companion.py
aidol/schemas/__init__.py
aidol/schemas/aidol.py
aidol/schemas/aidol_lead.py
aidol/schemas/companion.py
aidol/services/__init__.py
aidol/services/companion_service.py
aidol/services/image_generation_service.py
py_aidol-0.3.0.dist-info/METADATA
py_aidol-0.3.0.dist-info/WHEEL
py_aidol-0.3.0.dist-info/RECORD
