Metadata-Version: 2.4
Name: py-aidol
Version: 0.3.0
Summary: Create and chat with your own AI idol group
License: Apache-2.0
Keywords: kpop,idol,aidol,ai-companion,chatbot,image-generation
Author: AIoIA, Inc.
Author-email: devops@aioia.ai
Requires-Python: >=3.10,<3.13
Classifier: License :: OSI Approved :: Apache Software License
Classifier: Programming Language :: Python :: 3
Classifier: Programming Language :: Python :: 3.10
Classifier: Programming Language :: Python :: 3.11
Classifier: Programming Language :: Python :: 3.12
Requires-Dist: aioia-core (>=2.2.0,<3.0.0)
Requires-Dist: fastapi (>=0.115.12,<0.116.0)
Requires-Dist: google-genai (>=1.60.0,<2.0.0)
Requires-Dist: httpx (>=0.28.1,<0.29.0)
Requires-Dist: openai (>=1.0.0)
Requires-Dist: pillow (>=10.0.0,<11.0.0)
Requires-Dist: psycopg2-binary (>=2.9.9,<3.0.0)
Requires-Dist: pydantic-settings (>=2.1.0,<3.0.0)
Requires-Dist: pydantic[email] (>=2.5.3,<3.0.0)
Requires-Dist: pyhumps (>=3.8.0,<4.0.0)
Requires-Dist: python-dotenv (>=1.0.0,<2.0.0)
Requires-Dist: sqlalchemy (>=2.0.25,<3.0.0)
Requires-Dist: sqlalchemy-mixins (>=2.0.5,<3.0.0)
